hisel/__init__.py
hisel/categorical.py
hisel/cudakernels.py
hisel/feature_selection.py
hisel/hsic.py
hisel/kernels.py
hisel/lar/__init__.py
hisel/lar/_lar.pxd
hisel/lar/_lar.pyx
hisel/lar/lar.py
hisel/permutohedron.py
hisel/select.py
hisel-1.0.0.dist-info/LICENSE.txt
hisel-1.0.0.dist-info/METADATA
hisel-1.0.0.dist-info/WHEEL
hisel-1.0.0.dist-info/RECORD
