Metadata-Version: 2.1
Name: hisel
Version: 1.0.0
Summary: 
Author: claudio
Author-email: claudio.bellani@transferwise.com
Requires-Python: >=3.8,<3.12
Classifier: Programming Language :: Python :: 3
Classifier: Programming Language :: Python :: 3.8
Classifier: Programming Language :: Python :: 3.9
Classifier: Programming Language :: Python :: 3.10
Classifier: Programming Language :: Python :: 3.11
Provides-Extra: cuda102
Provides-Extra: cuda110
Provides-Extra: cuda111
Provides-Extra: cuda11x
Provides-Extra: cuda12x
Requires-Dist: cupy-cuda102 ; extra == "cuda102"
Requires-Dist: cupy-cuda110 ; extra == "cuda110"
Requires-Dist: cupy-cuda111 ; extra == "cuda111"
Requires-Dist: cupy-cuda11x ; extra == "cuda11x"
Requires-Dist: cupy-cuda12x ; extra == "cuda12x"
Requires-Dist: numpy (>=1.22)
Requires-Dist: pandas (>=1.5.3)
Requires-Dist: scikit-learn (>=1.2.0)
Requires-Dist: scipy (>=1.10)
Requires-Dist: tqdm
